ai4s/__init__.py
ai4s/jobq/__init__.py
ai4s/jobq/aiomp.py
ai4s/jobq/auth.py
ai4s/jobq/blob.py
ai4s/jobq/blob_stash.py
ai4s/jobq/cli.py
ai4s/jobq/entities.py
ai4s/jobq/jobq.py
ai4s/jobq/la_workspace.py
ai4s/jobq/logging_utils.py
ai4s/jobq/py.typed
ai4s/jobq/scheduled_events.py
ai4s/jobq/work.py
ai4s/jobq/backend/__init__.py
ai4s/jobq/backend/common.py
ai4s/jobq/backend/servicebus.py
ai4s/jobq/backend/storage_queue.py
ai4s/jobq/examples/__init__.py
ai4s/jobq/ext/__init__.py
ai4s/jobq/ext/amlt_utils.py
ai4s/jobq/ext/background_dirsync.py
ai4s/jobq/ext/map_in_config.py
ai4s/jobq/orchestration/__init__.py
ai4s/jobq/orchestration/manager.py
ai4s/jobq/orchestration/multiregion_workforce.py
ai4s/jobq/orchestration/pid_file.py
ai4s/jobq/orchestration/workforce.py
ai4s/jobq/orchestration/workforce_monitor.py
ai4s/jobq/track/__init__.py
ai4s/jobq/track/app.py
ai4s/jobq/track/config.py
ai4s/jobq/track/assets/solarized.css
ai4s/jobq/track/components/__init__.py
ai4s/jobq/track/components/active_workers.py
ai4s/jobq/track/components/cpu_utilization.py
ai4s/jobq/track/components/errors.py
ai4s/jobq/track/components/preemption_events.py
ai4s/jobq/track/components/queue_size.py
ai4s/jobq/track/components/ram_utilization.py
ai4s/jobq/track/components/task_runtimes.py
ai4s/jobq/track/components/tasks_completed.py
ai4s/jobq/track/components/tasks_starting.py
ai4s/jobq/track/utils/__init__.py
ai4s/jobq/track/utils/log_analytics.py
ai4s_jobq-2.15.1.dist-info/licenses/LICENSE
ai4s_jobq-2.15.1.dist-info/METADATA
ai4s_jobq-2.15.1.dist-info/WHEEL
ai4s_jobq-2.15.1.dist-info/entry_points.txt
ai4s_jobq-2.15.1.dist-info/top_level.txt
ai4s_jobq-2.15.1.dist-info/RECORD
