Metadata-Version: 2.4
Name: ai4s-jobq
Version: 2.15.1
Summary: AI for Science Job Queue - A distributed job queue system for large scale embarassingly parallel workloads
Project-URL: repository, https://github.com/microsoft/ai4s-jobq
Requires-Python: >=3.10
License-File: LICENSE
Requires-Dist: aiohttp
Requires-Dist: rich
Requires-Dist: asyncclick<8.2.2
Requires-Dist: azure-identity
Requires-Dist: azure-monitor-opentelemetry
Requires-Dist: azure-storage-blob
Requires-Dist: azure-storage-queue
Requires-Dist: psutil
Requires-Dist: types-python-dateutil
Requires-Dist: joblib
Requires-Dist: anyio
Requires-Dist: pyyaml
Requires-Dist: cachetools
Requires-Dist: azure-servicebus
Requires-Dist: appdirs
Provides-Extra: dev
Requires-Dist: tox; extra == "dev"
Requires-Dist: tox-conda; extra == "dev"
Requires-Dist: pytest; extra == "dev"
Requires-Dist: pytest-asyncio; extra == "dev"
Requires-Dist: pytest-mock; extra == "dev"
Requires-Dist: wait-for-it; extra == "dev"
Requires-Dist: types-psutil; extra == "dev"
Requires-Dist: types-cachetools; extra == "dev"
Requires-Dist: pandas-stubs; extra == "dev"
Requires-Dist: plotly-stubs; extra == "dev"
Requires-Dist: sphinx; extra == "dev"
Requires-Dist: sphinx-autodoc-typehints; extra == "dev"
Requires-Dist: sphinx-rtd-theme; extra == "dev"
Requires-Dist: toml; extra == "dev"
Requires-Dist: types-toml; extra == "dev"
Requires-Dist: myst-parser; extra == "dev"
Requires-Dist: sphinx-sitemap; extra == "dev"
Requires-Dist: sphinx-prompt; extra == "dev"
Requires-Dist: sphinx-copybutton; extra == "dev"
Requires-Dist: sphinx_markdown_builder; extra == "dev"
Provides-Extra: workforce
Requires-Dist: azure-ai-ml; extra == "workforce"
Requires-Dist: pydantic; extra == "workforce"
Provides-Extra: servicebus
Requires-Dist: azure-servicebus; extra == "servicebus"
Provides-Extra: track
Requires-Dist: dash_bootstrap_components; extra == "track"
Requires-Dist: dash; extra == "track"
Requires-Dist: pandas; extra == "track"
Requires-Dist: azure-monitor-query; extra == "track"
Requires-Dist: azure-mgmt-resourcegraph; extra == "track"
Requires-Dist: azure-mgmt-loganalytics; extra == "track"
Dynamic: license-file
